os_signpost/__init__.py
os_signpost/cy.cpython-38-darwin.so
os_signpost/cy.pxd
os_signpost/cy.pyx
os_signpost/signpost_wrap.h
os_signpost/tests/__init__.py
os_signpost/tests/test_signposter.py
os_signpost-0.0.3.dist-info/LICENSE
os_signpost-0.0.3.dist-info/METADATA
os_signpost-0.0.3.dist-info/WHEEL
os_signpost-0.0.3.dist-info/top_level.txt
os_signpost-0.0.3.dist-info/zip-safe
os_signpost-0.0.3.dist-info/RECORD
